feldman_vss.py
postquantum_feldman_vss-0.8.0b3.dist-info/LICENSE
postquantum_feldman_vss-0.8.0b3.dist-info/METADATA
postquantum_feldman_vss-0.8.0b3.dist-info/WHEEL
postquantum_feldman_vss-0.8.0b3.dist-info/top_level.txt
postquantum_feldman_vss-0.8.0b3.dist-info/RECORD
