Metadata-Version: 2.2
Name: PostQuantum-Feldman-VSS
Version: 0.8.0b3
Summary: Post-Quantum Secure Feldman's Verifiable Secret Sharing (VSS) in Python
Author-email: David Osipov <personal@david-osipov.vision>
Maintainer-email: David Osipov <personal@david-osipov.vision>
License: MIT
Project-URL: Homepage, https://github.com/DavidOsipov/PostQuantum-Feldman-VSS
Project-URL: Issues, https://github.com/DavidOsipov/PostQuantum-Feldman-VSS/issues
Project-URL: Source, https://github.com/DavidOsipov/PostQuantum-Feldman-VSS
Project-URL: documentation, https://github.com/DavidOsipov/PostQuantum-Feldman-VSS/wiki
Project-URL: Security Advisories, https://github.com/DavidOsipov/PostQuantum-Feldman-VSS/security/advisories
Project-URL: Security Policy, https://github.com/DavidOsipov/PostQuantum-Feldman-VSS/security/policy
Project-URL: Personal Website, https://david-osipov.vision
Project-URL: LinkedIn, https://www.linkedin.com/in/david-osipov
Project-URL: GitHub Profile, https://github.com/DavidOsipov
Project-URL: ISNI, https://isni.org/isni/000000051802960X
Project-URL: ORCID, https://orcid.org/0009-0005-2713-9242
Project-URL: Telegram, https://telegram.me/david_osipov
Project-URL: Signal, https://signal.me/#eu/d68l1UjrWlGVRzbfkVM1bvQMNqCqiae9GM86P_af8ZK2o5E5YSNKbL4MyM9y-2WH
Classifier: Development Status :: 4 - Beta
Classifier: Intended Audience :: Developers
Classifier: License :: OSI Approved :: MIT License
Classifier: Operating System :: OS Independent
Classifier: Programming Language :: Python :: 3
Classifier: Programming Language :: Python :: 3.8
Classifier: Programming Language :: Python :: 3.9
Classifier: Programming Language :: Python :: 3.10
Classifier: Programming Language :: Python :: 3.11
Classifier: Programming Language :: Python :: 3.12
Classifier: Topic :: Security
Classifier: Topic :: Security :: Cryptography
Classifier: Topic :: Software Development :: Libraries :: Python Modules
Requires-Python: >=3.8
License-File: LICENSE
Requires-Dist: gmpy2==2.2.1
Requires-Dist: msgpack==1.1.0
Requires-Dist: blake3==1.0.4; platform_system != "Emscripten"
Provides-Extra: memory-monitor
Requires-Dist: psutil==7.0.0; extra == "memory-monitor"
Provides-Extra: test
Requires-Dist: pytest>=7.0; extra == "test"
Requires-Dist: pytest-cov>=4.0; extra == "test"
Requires-Dist: pytest-xdist>=3.0; extra == "test"
Requires-Dist: hypothesis>=6.0; extra == "test"
Provides-Extra: docs
Requires-Dist: sphinx>=7.0; extra == "docs"
Requires-Dist: sphinx-rtd-theme>=2.0; extra == "docs"
Requires-Dist: myst-parser>=2.0; extra == "docs"
Requires-Dist: sphinx-copybutton>=0.5; extra == "docs"
Requires-Dist: sphinx-autodoc-typehints>=2.0; extra == "docs"
Provides-Extra: dev
Requires-Dist: black>=24.0; extra == "dev"
Requires-Dist: isort>=5.10; extra == "dev"
Requires-Dist: flake8>=7.0; extra == "dev"
Requires-Dist: mypy>=1.9; extra == "dev"
Requires-Dist: pre-commit>=3.6; extra == "dev"
Requires-Dist: types-requests; extra == "dev"
Requires-Dist: types-setuptools; extra == "dev"
Requires-Dist: msgpack-types==0.5.0; extra == "dev"
